requirements.in
sshmitm/__init__.py
sshmitm/__main__.py
sshmitm/authentication.py
sshmitm/cli.py
sshmitm/config.py
sshmitm/console.py
sshmitm/exceptions.py
sshmitm/logger.py
sshmitm/multisocket.py
sshmitm/session.py
sshmitm/utils.py
sshmitm/apps/__init__.py
sshmitm/apps/mosh.py
sshmitm/audit/__init__.py
sshmitm/audit/cli.py
sshmitm/clients/__init__.py
sshmitm/clients/sftp.py
sshmitm/clients/ssh.py
sshmitm/commands/__init__.py
sshmitm/commands/check_publickey.py
sshmitm/data/client_info.yml
sshmitm/data/default.ini
sshmitm/forwarders/__init__.py
sshmitm/forwarders/agent.py
sshmitm/forwarders/base.py
sshmitm/forwarders/scp.py
sshmitm/forwarders/sftp.py
sshmitm/forwarders/ssh.py
sshmitm/forwarders/tunnel.py
sshmitm/interfaces/__init__.py
sshmitm/interfaces/server.py
sshmitm/interfaces/sftp.py
sshmitm/moduleparser/__init__.py
sshmitm/moduleparser/baseparser.py
sshmitm/moduleparser/exceptions.py
sshmitm/moduleparser/formatter.py
sshmitm/moduleparser/modules.py
sshmitm/moduleparser/parser.py
sshmitm/moduleparser/utils.py
sshmitm/plugins/__init__.py
sshmitm/plugins/scp/__init__.py
sshmitm/plugins/scp/cve202229154.py
sshmitm/plugins/scp/debug_traffic.py
sshmitm/plugins/scp/inject_file.py
sshmitm/plugins/scp/replace_file.py
sshmitm/plugins/scp/rewrite_command.py
sshmitm/plugins/scp/store_file.py
sshmitm/plugins/session/__init__.py
sshmitm/plugins/session/clientaudit.py
sshmitm/plugins/session/cve202014002.py
sshmitm/plugins/session/cve202014145.py
sshmitm/plugins/session/key_negotiation.py
sshmitm/plugins/session/server_host_key_algorithms.py
sshmitm/plugins/session/tcpserver.py
sshmitm/plugins/sftp/__init__.py
sshmitm/plugins/sftp/replace_file.py
sshmitm/plugins/sftp/store_file.py
sshmitm/plugins/ssh/__init__.py
sshmitm/plugins/ssh/mirrorshell.py
sshmitm/plugins/ssh/terminallogs.py
sshmitm/plugins/tunnel/__init__.py
sshmitm/plugins/tunnel/injectservertunnel.py
sshmitm/plugins/tunnel/socks.py
sshmitm/plugins/tunnel/socks4.py
sshmitm/plugins/tunnel/socks5.py
ssh_mitm-5.0.1.dist-info/METADATA
ssh_mitm-5.0.1.dist-info/WHEEL
ssh_mitm-5.0.1.dist-info/entry_points.txt
ssh_mitm-5.0.1.dist-info/licenses/LICENSE
ssh_mitm-5.0.1.dist-info/RECORD
