Metadata-Version: 2.4
Name: ssh-mitm
Version: 5.0.1
Summary: ssh mitm server for security audits supporting publickey authentication, session hijacking and file manipulation
Project-URL: Homepage, https://www.ssh-mitm.at
Project-URL: Documentation, https://docs.ssh-mitm.at
Project-URL: Changelog, https://github.com/ssh-mitm/ssh-mitm/blob/master/CHANGELOG.md
Project-URL: Source, https://github.com/ssh-mitm/ssh-mitm
Project-URL: Tracker, https://github.com/ssh-mitm/ssh-mitm/issues
Author-email: SSH-MITM Dev-Team <support@ssh-mitm.at>
Maintainer-email: Manfred Kaiser <manfred.kaiser@ssh-mitm.at>
License:                     GNU GENERAL PUBLIC LICENSE
License-File: LICENSE
Keywords: audit,mitm,network,proxy,security,ssh
Classifier: Development Status :: 5 - Production/Stable
Classifier: License :: OSI Approved :: GNU General Public License v3 (GPLv3)
Classifier: Programming Language :: Python :: 3
Classifier: Programming Language :: Python :: 3.8
Classifier: Programming Language :: Python :: 3.9
Classifier: Programming Language :: Python :: 3.10
Classifier: Programming Language :: Python :: 3.11
Classifier: Programming Language :: Python :: 3.12
Classifier: Topic :: System :: Networking
Requires-Python: >=3.8
Requires-Dist: appimage
Requires-Dist: argcomplete
Requires-Dist: colored
Requires-Dist: importlib-metadata>=4.6; python_version < '3.10'
Requires-Dist: importlib-resources>=5.0; python_version < '3.10'
Requires-Dist: packaging
Requires-Dist: paramiko<3.5,>=3.4
Requires-Dist: python-json-logger
Requires-Dist: pytz
Requires-Dist: pyyaml
Requires-Dist: rich
Requires-Dist: sshpubkeys
Requires-Dist: wrapt
